Tests/__init__.py
Tests/test_brain_loader.py
Tests/test_configuration_checker.py
Tests/test_cortex.py
Tests/test_dna_loader.py
Tests/test_dynamic_loading.py
Tests/test_file_manager.py
Tests/test_hook_manager.py
Tests/test_init.py
Tests/test_lifo_buffer.py
Tests/test_models.py
Tests/test_neuron_launcher.py
Tests/test_neuron_module.py
Tests/test_neuron_parameter_loader.py
Tests/test_notification_manager.py
Tests/test_order_analyser.py
Tests/test_order_listener.py
Tests/test_player_launcher.py
Tests/test_resources_manager.py
Tests/test_rest_api.py
Tests/test_setting_editor.py
Tests/test_settings_loader.py
Tests/test_singleton.py
Tests/test_synapse_launcher.py
Tests/test_trigger_launcher.py
Tests/test_tts_module.py
Tests/test_utils.py
Tests/test_yaml_loader.py
kalliope/__init__.py
kalliope/_version.py
kalliope/brain.yml
kalliope/settings.yml
kalliope/core/Cortex.py
kalliope/core/HookManager.py
kalliope/core/NeuronExceptions.py
kalliope/core/NeuronLauncher.py
kalliope/core/NeuronModule.py
kalliope/core/NeuronParameterLoader.py
kalliope/core/NotificationManager.py
kalliope/core/OrderAnalyser.py
kalliope/core/OrderListener.py
kalliope/core/PlayerLauncher.py
kalliope/core/PlayerModule.py
kalliope/core/ResourcesManager.py
kalliope/core/SignalLauncher.py
kalliope/core/SignalModule.py
kalliope/core/SynapseLauncher.py
kalliope/core/TriggerLauncher.py
kalliope/core/__init__.py
kalliope/core/ConfigurationManager/BrainLoader.py
kalliope/core/ConfigurationManager/ConfigurationChecker.py
kalliope/core/ConfigurationManager/DnaLoader.py
kalliope/core/ConfigurationManager/SettingEditor.py
kalliope/core/ConfigurationManager/SettingLoader.py
kalliope/core/ConfigurationManager/YAMLLoader.py
kalliope/core/ConfigurationManager/__init__.py
kalliope/core/Lifo/LIFOBuffer.py
kalliope/core/Lifo/LifoManager.py
kalliope/core/Lifo/__init__.py
kalliope/core/Models/APIResponse.py
kalliope/core/Models/Brain.py
kalliope/core/Models/Dna.py
kalliope-0.5.3.dist-info/DESCRIPTION.rst
kalliope-0.5.3.dist-info/METADATA
kalliope-0.5.3.dist-info/RECORD
kalliope-0.5.3.dist-info/WHEEL
kalliope-0.5.3.dist-info/entry_points.txt
kalliope-0.5.3.dist-info/metadata.json
kalliope-0.5.3.dist-info/top_level.txt
